pharmacology_mcp/__init__.py
pharmacology_mcp/local.py
pharmacology_mcp/pharmacology_api.py
pharmacology_mcp/server.py
pharmacology_mcp-0.1.3.dist-info/METADATA
pharmacology_mcp-0.1.3.dist-info/WHEEL
pharmacology_mcp-0.1.3.dist-info/entry_points.txt
pharmacology_mcp-0.1.3.dist-info/licenses/LICENSE
pharmacology_mcp-0.1.3.dist-info/RECORD
