Metadata-Version: 2.4
Name: pharmacology-mcp
Version: 0.1.3
Summary: MCP for Guide to Pharmacology database
Author-email: antonkulaga <antonkulaga@gmail.com>
License-File: LICENSE
Requires-Python: >=3.10
Requires-Dist: aiosqlite>=0.21.0
Requires-Dist: anyio>=4.9.0
Requires-Dist: eliot>=1.17.5
Requires-Dist: fastapi>=0.116.0
Requires-Dist: fastmcp>=2.10.3
Requires-Dist: httpx>=0.28.1
Requires-Dist: huggingface-hub>=0.33.2
Requires-Dist: pycomfort>=0.0.18
Requires-Dist: pydantic>=2.11.7
Requires-Dist: pygtop>=2.1.5
Requires-Dist: python-dotenv>=1.1.1
Requires-Dist: sqlite-utils>=3.38
Requires-Dist: typer>=0.16.0
